{
  "added": "2013-04-06T14:03:59Z", 
  "copyright_text": "CC BY 3.0", 
  "description": "", 
  "embed": "<object width=\"640\" height=\"390\"><param name=\"movie\" value=\"http://youtube.com/v/NdcBKdaPVbE?version=3&amp;hl=en_US\"></param><param name=\"allowFullScreen\" value=\"true\"></param><param name=\"allowscriptaccess\" value=\"always\"></param><embed src=\"http://youtube.com/v/NdcBKdaPVbE?version=3&amp;hl=en_US\" type=\"application/x-shockwave-flash\" width=\"640\" height=\"390\" allowscriptaccess=\"always\" allowfullscreen=\"true\"></embed></object>", 
  "language": "English", 
  "quality_notes": "", 
  "recorded": "2011-10-07T14:43:58Z", 
  "slug": "", 
  "source_url": "http://www.youtube.com/watch?v=NdcBKdaPVbE", 
  "speakers": [
    "Yannick Gingras"
  ], 
  "state": 2, 
  "summary": "", 
  "tags": [
    "MP02"
  ], 
  "thumbnail_url": "http://i.ytimg.com/vi/NdcBKdaPVbE/hqdefault.jpg", 
  "title": "PyQt and PyOpenGL", 
  "whiteboard": ""
}